{
    "web": {
        "client_id": "358725497087-6e4j5773cku9g15bei3b40pa93huc4lp.apps.googleusercontent.com",
        "project_id": "project1-355708",
        "auth_uri": "https://accounts.google.com/o/oauth2/auth",
        "token_uri": "https://oauth2.googleapis.com/token",
        "auth_provider_x509_cert_url": "https://www.googleapis.com/oauth2/v1/certs",
        "client_secret": "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",
        "redirect_uris": [
            "http://localhost:8080/"
        ]
    }
}